cinder/__init__.py
modbamtools/__init__.py
modbamtools/calcregions.py
modbamtools/cli.py
modbamtools/clustering.py
modbamtools/gene_models.py
modbamtools/heterogeneity.py
modbamtools/modbamviz.py
modbamtools/tracks.py
modbamtools/tracks_webgl.py
modbamtools/utils.py
modbamtools-0.4.8.dist-info/LICENSE
modbamtools-0.4.8.dist-info/METADATA
modbamtools-0.4.8.dist-info/WHEEL
modbamtools-0.4.8.dist-info/entry_points.txt
modbamtools-0.4.8.dist-info/top_level.txt
modbamtools-0.4.8.dist-info/RECORD
