Metadata-Version: 2.1
Name: modbamtools
Version: 0.4.8
Summary: A set of tools to manipulate and visualize data from base modification bam files
Home-page: https://github.com/rrazaghi/modbamtools
Author: Roham Razaghi
License: Apache License, Version 2.0
Project-URL: Issues, https://github.com/rrazaghi/modbamtools/issues
Project-URL: CI, https://github.com/rrazaghi/modbamtools/actions
Project-URL: Changelog, https://github.com/rrazaghi/modbamtools/releases
Requires-Python: >=3.8, <=3.10.5
License-File: LICENSE
Requires-Dist: click (>=8.0.4)
Requires-Dist: pysam (>=0.18.0)
Requires-Dist: scipy (>=1.7.0)
Requires-Dist: pandas (>=1.4.0)
Requires-Dist: numpy (>=1.22.0)
Requires-Dist: plotly (>=5.5.0)
Requires-Dist: modbampy (==0.5.3)
Requires-Dist: kaleido (>=0.2.1)
Requires-Dist: pyBigWig (>=0.3.18)
Requires-Dist: PyPDF2
Requires-Dist: pillow
Requires-Dist: hdbscan
Requires-Dist: tqdm
Provides-Extra: test
Requires-Dist: pytest ; extra == 'test'
